pbrenko.py
pbrenko-0.0.3.dist-info/METADATA
pbrenko-0.0.3.dist-info/WHEEL
pbrenko-0.0.3.dist-info/top_level.txt
pbrenko-0.0.3.dist-info/RECORD
