Metadata-Version: 2.1
Name: pbrenko
Version: 0.0.3
Summary: Percent based Renko chart creator.
Home-page: https://github.com/aticio/pbrenko
Author: Özgür Atıcı
Author-email: aticiozgur@gmail.com
License: UNKNOWN
Platform: UNKNOWN
Classifier: Programming Language :: Python :: 3
Classifier: License :: OSI Approved :: MIT License
Classifier: Operating System :: OS Independent
Provides-Extra: dev
Requires-Dist: pytest (>=3.7) ; extra == 'dev'
